flex_pubsub/__init__.py
flex_pubsub/app_settings.py
flex_pubsub/apps.py
flex_pubsub/backends.py
flex_pubsub/checks.py
flex_pubsub/constants.py
flex_pubsub/publisher.py
flex_pubsub/scheduler.py
flex_pubsub/subscription.py
flex_pubsub/tasks.py
flex_pubsub/tests.py
flex_pubsub/utils.py
flex_pubsub/management/commands/run_sub.py
flex_pubsub/migrations/__init__.py
flex_pubsub/types/__init__.py
flex_pubsub/types/backends.py
flex_pubsub/types/scheduler.py
django_flex_pubsub-0.0.17.dist-info/AUTHORS.rst
django_flex_pubsub-0.0.17.dist-info/LICENSE
django_flex_pubsub-0.0.17.dist-info/METADATA
django_flex_pubsub-0.0.17.dist-info/WHEEL
django_flex_pubsub-0.0.17.dist-info/top_level.txt
django_flex_pubsub-0.0.17.dist-info/RECORD
