Metadata-Version: 2.1
Name: django-flex-pubsub
Version: 0.0.17
Summary: Django project for using Google Cloud Pub/Sub for handling background and scehduler tasks
Author-email: Saman Zand Haghighi <samanzandh@gmail.com>, Ali Avani <ali.avani@outlook.com>
Maintainer-email: Saman Zand Haghighi <samanzandh@gmail.com>, Ali Avani <ali.avani@outlook.com>
License: MIT license
Project-URL: bugs, https://github.com/ali-avani/django-flex-pubsub/issues
Project-URL: changelog, https://github.com/ali-avani/django-flex-pubsub/blob/master/changelog.md
Project-URL: homepage, https://github.com/ali-avani/django-flex-pubsub
License-File: LICENSE
License-File: AUTHORS.rst
Provides-Extra: dev
Requires-Dist: coverage; extra == "dev"
Requires-Dist: mypy; extra == "dev"
Requires-Dist: pytest; extra == "dev"
Requires-Dist: ruff; extra == "dev"
